LICENSE
MANIFEST.in
README
setup.cfg
setup.py
./jenny/jenny.c
demo/__init__.py
demo/__init__.pyc
demo/demo_app.py
demo/demo_app.pyc
demo/test_demo_app.py
demo/test_demo_app.pyc
grandma/__init__.py
grandma/grandma.py
grandma/jenny_repl.py
grandma/jenny_wrapper.py
grandma.egg-info/PKG-INFO
grandma.egg-info/SOURCES.txt
grandma.egg-info/dependency_links.txt
grandma.egg-info/not-zip-safe
grandma.egg-info/top_level.txt
tests/__init__.py
tests/__init__.pyc
tests/chart_sin.png
tests/chart_sin.py
tests/chart_sin_error.png
tests/chart_sin_error.py
tests/chart_sin_wrong.png
tests/chart_sin_wrong.py
tests/chart_ziggzagg.png
tests/chart_ziggzagg.py
tests/sample_sut.py
tests/sample_sut.pyc
tests/sample_sut_sin.py
tests/sample_sut_sin.pyc
tests/sample_sut_sin_error.py
tests/sample_sut_sin_error.pyc
tests/sample_sut_sin_wrong.py
tests/sample_sut_sin_wrong.pyc
tests/sample_sut_ziggzagg.py
tests/sample_sut_ziggzagg.pyc
tests/test_grandma.py
tests/test_grandma.pyc
tests/test_jenny.py
tests/test_jenny.pyc
tests/test_sin_sut.pyc
tests/test_sut.py
tests/test_sut.pyc
tests/test_sut_sin.py
tests/test_sut_sin.pyc