Metadata-Version: 1.0
Name: grandma
Version: 0.1a2
Summary: grandma is used for combinatorial testing
Home-page: http://github.com/markfink/grandma
Author: Mark Fink
Author-email: mark@mark-fink.de
License: GNU LESSER GENERAL PUBLIC LICENSE, Version 3
Download-URL: http://pypi.python.org/pypi/grandma
Platform: any
Classifier: License :: OSI Approved :: GNU Library or Lesser General Public License (LGPL)
Classifier: Intended Audience :: Developers
Classifier: Intended Audience :: System Administrators
Classifier: Development Status :: 3 - Alpha
Classifier: Programming Language :: Python
Classifier: Programming Language :: Python :: 2
Classifier: Operating System :: OS Independent
Classifier: Topic :: Software Development :: Testing
Classifier: Natural Language :: English
